mesiqi/__init__.py
mesiqi/__main__.py
mesiqi/core/__init__.py
mesiqi/core/connector.py
mesiqi/core/connector_factory.py
mesiqi/core/connector_loader.py
mesiqi/core/engine.py
mesiqi/core/jobfactory.py
mesiqi/core/jobs.py
mesiqi/core/logger.py
mesiqi/core/utils.py
mesiqi/framework/__init__.py
mesiqi/framework/cli/__init__.py
mesiqi/framework/cli/cli.py
mesiqi/plugins/__init__.py
mesiqi/plugins/bigquery.py
mesiqi/plugins/snowflake.py
mesiqi/plugins/sqldb.py
mesiqi/secrets/__init__.py
mesiqi/secrets/set_env.py
mesiqi-0.0.2.dist-info/METADATA
mesiqi-0.0.2.dist-info/WHEEL
mesiqi-0.0.2.dist-info/entry_points.txt
mesiqi-0.0.2.dist-info/top_level.txt
mesiqi-0.0.2.dist-info/RECORD
