Metadata-Version: 2.1
Name: mesiqi
Version: 0.0.2
Summary: mesiqi helps you build data microservices
Home-page: https://github.com/mesiqi/mesiqi
Author: mesiqi
Author-email: mesiqi@mesiqi.com
License: UNKNOWN
Keywords: data microservices,data products,data pipelines,datamesh,ETL,ELT
Platform: UNKNOWN
Classifier: Development Status :: 2 - Pre-Alpha
Classifier: Programming Language :: Python :: 3.7
Classifier: Programming Language :: Python :: 3.8
Classifier: Programming Language :: Python :: 3.9
Requires-Python: >=3.7
Requires-Dist: requests (<2.26,>=2.20)
Requires-Dist: pandas (>=1.3.3)
Requires-Dist: snowflake-connector-python[secure-local-storage] (<2.6.0,>=2.4.1)
Requires-Dist: sqlalchemy (==1.4.25)
Requires-Dist: sqlalchemy-bigquery (==1.2.0)
Requires-Dist: snowflake-sqlalchemy (==1.3.2)
Requires-Dist: google-cloud-bigquery (==2.28.1)
Requires-Dist: google-cloud-bigquery-storage (==2.9.1)
Requires-Dist: google-auth (<3.0.0dev,>=1.25.0)
Requires-Dist: click (<8.0,<=7)
Requires-Dist: pydantic (<=1.7.4)
Requires-Dist: pyarrow (<3.1.0,>=3.0.0)
Requires-Dist: google-api-core (<2,>=1.16.0)
Requires-Dist: google-cloud-core (<2,>=1.3.0)
Requires-Dist: dbt (==0.21.0)
Requires-Dist: prefect (==0.15.7)
Requires-Dist: python-json-logger (>2.0)
Provides-Extra: all
Requires-Dist: Jinja2 (==2.11.3) ; extra == 'all'
Requires-Dist: cffi (<2.0.0,>=1.9) ; extra == 'all'
Requires-Dist: click (<9,>=8) ; extra == 'all'
Requires-Dist: idna (<4,>=2.5) ; extra == 'all'
Requires-Dist: isodate (<0.7,>=0.6) ; extra == 'all'
Requires-Dist: logbook (<1.6,>=1.5) ; extra == 'all'
Requires-Dist: packaging (<22.0,>=20.9) ; extra == 'all'
Requires-Dist: requests (<3.0.0) ; extra == 'all'
Requires-Dist: sqlparse (<0.5,>=0.2.3) ; extra == 'all'
Requires-Dist: typing-extensions (<3.11,>=3.7.4) ; extra == 'all'
Requires-Dist: dataclasses (<0.9,>=0.6) ; (python_version < "3.7") and extra == 'all'
Provides-Extra: dbt
Requires-Dist: Jinja2 (==2.11.3) ; extra == 'dbt'
Requires-Dist: click (<9,>=8) ; extra == 'dbt'
Requires-Dist: isodate (<0.7,>=0.6) ; extra == 'dbt'
Requires-Dist: logbook (<1.6,>=1.5) ; extra == 'dbt'
Requires-Dist: packaging (<22.0,>=20.9) ; extra == 'dbt'
Requires-Dist: sqlparse (<0.5,>=0.2.3) ; extra == 'dbt'
Requires-Dist: typing-extensions (<3.11,>=3.7.4) ; extra == 'dbt'
Requires-Dist: dataclasses (<0.9,>=0.6) ; (python_version < "3.7") and extra == 'dbt'
Provides-Extra: snowflake
Requires-Dist: cffi (<2.0.0,>=1.9) ; extra == 'snowflake'
Requires-Dist: idna (<4,>=2.5) ; extra == 'snowflake'
Requires-Dist: requests (<3.0.0) ; extra == 'snowflake'
